sinapsis_darts_forecasting/__init__.py
sinapsis_darts_forecasting/helpers/__init__.py
sinapsis_darts_forecasting/helpers/tags.py
sinapsis_darts_forecasting/templates/__init__.py
sinapsis_darts_forecasting/templates/pandas_to_darts_base.py
sinapsis_darts_forecasting/templates/time_series_from_csv_loader.py
sinapsis_darts_forecasting/templates/time_series_from_dataframe_loader.py
sinapsis_darts_forecasting/templates/time_series_from_series_loader.py
sinapsis_darts_forecasting/templates/time_series_model.py
sinapsis_darts_forecasting/templates/time_series_preprocessing.py
sinapsis_darts_forecasting-0.1.10.dist-info/licenses/LICENSE
sinapsis_darts_forecasting-0.1.10.dist-info/METADATA
sinapsis_darts_forecasting-0.1.10.dist-info/WHEEL
sinapsis_darts_forecasting-0.1.10.dist-info/top_level.txt
sinapsis_darts_forecasting-0.1.10.dist-info/RECORD
