Metadata-Version: 2.4
Name: sinapsis-darts-forecasting
Version: 0.1.10
Summary: Module for handling time series data and forecasting using Darts.
Author-email: SinapsisAI <dev@sinapsis.tech>
Project-URL: Homepage, https://sinapsis.tech
Project-URL: Documentation, https://docs.sinapsis.tech/docs
Project-URL: Tutorials, https://docs.sinapsis.tech/tutorials
Project-URL: Repository, https://github.com/Sinapsis-AI/sinapsis-time-series.git
Requires-Python: >=3.10
License-File: LICENSE
Requires-Dist: sinapsis>=0.1.1
Provides-Extra: darts
Requires-Dist: u8darts[all]>=0.31.0; extra == "darts"
Provides-Extra: pandas
Requires-Dist: pandas>=2.2.3; extra == "pandas"
Provides-Extra: all
Requires-Dist: sinapsis-darts-forecasting[darts,pandas]; extra == "all"
Dynamic: license-file
